orjson_pydantic-3.6.7.dist-info/METADATA
orjson_pydantic-3.6.7.dist-info/WHEEL
orjson/__init__.py
orjson/__init__.pyi
orjson/py.typed
orjson/orjson.cpython-38-x86_64-linux-gnu.so
orjson_pydantic-3.6.7.dist-info/RECORD
