Metadata-Version: 2.1
Name: orjson-pydantic
Version: 3.6.7
Classifier: Development Status :: 5 - Production/Stable
Classifier: Intended Audience :: Developers
Classifier: License :: OSI Approved :: Apache Software License
Classifier: License :: OSI Approved :: MIT License
Classifier: Operating System :: MacOS
Classifier: Operating System :: Microsoft :: Windows
Classifier: Operating System :: POSIX :: Linux
Classifier: Programming Language :: Python :: 3
Classifier: Programming Language :: Python :: 3.10
Classifier: Programming Language :: Python :: 3.7
Classifier: Programming Language :: Python :: 3.8
Classifier: Programming Language :: Python :: 3.9
Classifier: Programming Language :: Python :: Implementation :: CPython
Classifier: Programming Language :: Python
Classifier: Programming Language :: Rust
Classifier: Typing :: Typed
Summary: Fast, correct Python JSON library supporting dataclasses, datetimes, and numpy
Keywords: fast,json,dataclass,dataclasses,datetime,rfc,8259,3339
Home-Page: https://github.com/aviramha/orjson-pydantic
Author: ijl <ijl@mailbox.org>, Aviram Hassan <aviramyhassan@gmail.com>
Author-email: ijl <ijl@mailbox.org>, Aviram Hassan <aviramyhassan@gmail.com>
License: Apache-2.0 OR MIT
Requires-Python: >=3.7
Project-URL: Source Code, https://github.com/aviramha/orjson-pydantic
